README.rst
setup.py
bin/javagt
bin/mdgt
bin/pygt
greptools/__init__.py
greptools/base.py
greptools/greptree.py
greptools/publisher.py
greptools/searcher.py
greptools.egg-info/PKG-INFO
greptools.egg-info/SOURCES.txt
greptools.egg-info/dependency_links.txt
greptools.egg-info/requires.txt
greptools.egg-info/top_level.txt
greptools/reader/__init__.py
greptools/reader/javareader.py
greptools/reader/markdownreader.py
greptools/reader/pythonreader.py
greptools/reader/reader.py
greptools/test/__init__.py
greptools/test/test_greptree.py
greptools/test/test_reader.py