Metadata-Version: 1.1
Name: greptools
Version: 0.9b0
Summary: A collection of grep wrappers and tools for various filetypes.
Home-page: https://github.com/nicr9/greptools
Author: Nic Roland
Author-email: nicroland9@gmail.com
License: MIT
Download-URL: https://github.com/nicr9/greptools/tarball/0.9b
Platform: UNKNOWN
Classifier: Development Status :: 4 - Beta
Classifier: Environment :: Console
Classifier: Intended Audience :: Developers
Classifier: License :: OSI Approved :: MIT License
Classifier: Natural Language :: English
Classifier: Operating System :: POSIX :: Linux
Classifier: Operating System :: MacOS :: MacOS X
Classifier: Programming Language :: Python :: 2.7
Classifier: Topic :: Software Development
Classifier: Topic :: Text Processing :: Filters
Classifier: Topic :: Utilities
